pymoai/__init__.py
pymoai/api/__init__.py
pymoai/api/commands.py
pymoai/api/datasets.py
pymoai/client.py
pymoai/config.py
pymoai/exceptions.py
pymoai/handlers.py
pymoai/schemas.py
pymoai-0.3.2.dist-info/LICENSE
pymoai-0.3.2.dist-info/METADATA
pymoai-0.3.2.dist-info/WHEEL
pymoai-0.3.2.dist-info/RECORD
