Metadata-Version: 2.1
Name: pymoai
Version: 0.3.2
Summary: MontOps AI Python Client
Home-page: https://www.montops.ai/
License: Apache-2.0
Keywords: AIOps,MLOps,ML Model Registry,ML Model Store,ML Monitoring
Author: montops.ai
Author-email: info@montops.ai
Requires-Python: >=3.8.1,<3.10
Classifier: Intended Audience :: Developers
Classifier: Intended Audience :: Science/Research
Classifier: License :: OSI Approved :: Apache Software License
Classifier: Natural Language :: English
Classifier: Operating System :: MacOS
Classifier: Operating System :: Microsoft :: Windows
Classifier: Operating System :: POSIX
Classifier: Operating System :: Unix
Classifier: Programming Language :: Python :: 3
Classifier: Programming Language :: Python :: 3.9
Classifier: Programming Language :: Python :: Implementation :: CPython
Classifier: Topic :: Scientific/Engineering :: Artificial Intelligence
Classifier: Topic :: Software Development :: Libraries :: Python Modules
Requires-Dist: boto3 (>=1.26.74,<2.0.0)
Requires-Dist: dacite (>=1.8.0,<2.0.0)
Requires-Dist: dataconf (>=2.1.3,<3.0.0)
Requires-Dist: numpy (==1.23.5)
Requires-Dist: pandas (>=1.4.3,<2.0.0)
Requires-Dist: pydantic (>=1.10.5,<2.0.0)
Requires-Dist: requests (>=2.28.2,<3.0.0)
Requires-Dist: requests-toolbelt (>=0.10.1,<0.11.0)
Requires-Dist: urllib3 (==1.25.11)
Project-URL: Repository, https://github.com/MontOpsInc/pymoai
